django_js_error_hook/__init__.py
django_js_error_hook/models.py
django_js_error_hook/tests.py
django_js_error_hook/urls.py
django_js_error_hook/views.py
django_js_error_hook/static/js/django_js_error_hook.js
django_js_error_hook-1.0.dist-info/AUTHORS
django_js_error_hook-1.0.dist-info/LICENCE
django_js_error_hook-1.0.dist-info/METADATA
django_js_error_hook-1.0.dist-info/WHEEL
django_js_error_hook-1.0.dist-info/top_level.txt
django_js_error_hook-1.0.dist-info/RECORD
