Metadata-Version: 2.1
Name: django-js-error-hook
Version: 1.0
Summary: Generic handler for hooking client side javascript error.
Home-page: https://github.com/jojax/django-js-error-hook
Author: Jonathan Dorival
Author-email: jonathan.dorival@novapost.fr
License: BSD
Keywords: class-based view,generic view,js error hooking
Platform: UNKNOWN
Classifier: Development Status :: 1 - Planning
Classifier: License :: OSI Approved :: BSD License
Classifier: Programming Language :: Python :: 3
Classifier: Framework :: Django
License-File: LICENCE
License-File: AUTHORS
Requires-Dist: django (>=3.2.0)
